<operator name="Root" class="Experiment">
  <description text="This learner uses a simple nearest neighbors classifier. This instance based classifiers just uses the other instances closest to the instance at hand in order to determine a prediction."/>
  <operator name="ArffExampleSource (2)" class="ArffExampleSource">
    <parameter key="data_file"	value="/home/fabricio/tancredo/2006-2o-semestre/inteligenciaArtificial/slidesAM/agrupamento/dados/iris.arff"/>
    <parameter key="label_attribute"	value="class"/>
  </operator>
  <operator name="WVTool" class="WVTool" activated="no">
    <parameter key="default_content_language"	value="portuguese"/>
    <list key="texts">
      <parameter key="users"	value="/home/fbarth/eclipse/workspace/XwikiRPC/data/users"/>
    </list>
  </operator>
  <operator name="IdTagging" class="IdTagging">
    <parameter key="create_nominal_ids"	value="true"/>
  </operator>
  <operator name="IBk" class="IBk">
    <parameter key="keep_example_set"	value="true"/>
  </operator>
  <operator name="ExampleVisualizer" class="ExampleVisualizer">
  </operator>
</operator>

